README.rst
setup.py
jumprun/__init__.py
python_jumprunpro.egg-info/PKG-INFO
python_jumprunpro.egg-info/SOURCES.txt
python_jumprunpro.egg-info/dependency_links.txt
python_jumprunpro.egg-info/requires.txt
python_jumprunpro.egg-info/top_level.txt