Metadata-Version: 1.1
Name: python-jumprunpro
Version: 0.0.2
Summary: Simple python bindings for scraping data from JumpRun Pro
Home-page: https://github.com/natemara/jumprunpro-python
Author: Nate Mara
Author-email: natemara@gmail.com
License: MIT
Keywords: skydiving manifest
Platform: UNKNOWN
Classifier: Development Status :: 3 - Alpha
Classifier: Topic :: Utilities
Classifier: License :: OSI Approved :: MIT License
Classifier: Intended Audience :: Developers
Classifier: Programming Language :: Python :: 2
Classifier: Programming Language :: Python :: 2.7
Classifier: Programming Language :: Python :: 3
Classifier: Programming Language :: Python :: 3.3
Classifier: Programming Language :: Python :: 3.4
